descripciones/motor/motor2.vhdl
-- Fecha: motor.vhdl
-- Author: Daniel
-- Date: 28 marzo, 2022 - 22:13:22 Argentina Standard Time
library ieee;
use ieee.std_logic_1164.all;

entity motor2 is
	port
	(
		-- Input ports
	a_i : in std_logic;
	clk : in std_logic;
	rst_i : in std_logic;
		-- Output ports
	b_o : out std_logic
	);
end entity motor2;

architecture fsm of motor2 is
-- Declarations (optional)
	type estado is (E1, A1, A2);
	signal actual, sigue : estado;
begin

secuencial:
process(clk)
begin
	if (clk'event and clk='1') then
		if rst_i='1' then
			actual <= A2;
		else
			actual <= sigue;
		end if;
	end if;
end process secuencial;

combinacional:
process(actual, a_i)
begin
	case actual is
		when E1 =>
			b_o <= '1';
			if (a_i = '1') then
				sigue <= A1;
			else
				sigue <= E1;
			end if;
		when A1 =>
			b_o <= '0';
			if (a_i = '1') then
				sigue <= A2;
			else
				sigue <= A1;
			end if;
		when A2 =>
			b_o <= '0';
			if (a_i = '1') then
				sigue <= E1;
			else
				sigue <= A2;
			end if;
		when others =>
			b_o <= '0';
			sigue <= A2;
		end case;
end process;

end architecture fsm;

descripciones/motor/motor2_tb.vhdl
library ieee;
use ieee.std_logic_1164.all;
use ieee.numeric_std.all;

entity motor2_tb is
end entity motor2_tb;
architecture test of motor2_tb is
	component motor2 is
	port
	(
	a_i : in std_logic;
	clk : in std_logic;
	rst_i : in std_logic;
	b_o : out std_logic
	);
	end component motor2;

	signal a_t : std_logic := '0';
	signal b_t : std_logic;
	signal clk_t : std_logic := '1';
	signal rst_t : std_logic := '1';
	constant FRECUENCIA : integer := 50;
	constant PERIODO : time := 1 us/FRECUENCIA;
	signal detener : boolean := false;

begin
dut: motor2 port map
	(
	a_i => a_t, clk => clk_t, b_o => b_t, rst_i => rst_t
	);

reloj:
process begin
	clk_t <= '1', '0' after PERIODO/2;
	wait for PERIODO;
	if detener then
		wait;
	end if;
end process reloj;

Prueba:
	process begin


		report "Verificando motor2" severity note;

		-- prueba estado inicial
		-- resetea maquina

		rst_t <= '1';
		wait for PERIODO;
		wait for 2 ns;
		rst_t <= '0';
		wait for PERIODO;
		wait until rising_edge(clk_t);
		wait for 2 ns;
		assert b_t = '0'
			report "Falla estado inicial A2" severity note;
		wait for PERIODO;

		-- prueba pasa a estado

		a_t <= '1';
		wait until rising_edge(clk_t);
		wait for 2 ns;
		assert b_t = '1'
			report "Falla transicion A2 -> E1" severity note;
	--	wait for 2 ns;
	--	wait for PERIODO;

		a_t <= '0';
		wait until rising_edge(clk_t);
		wait for 2 ns;
		assert b_t = '1'
			report "Falla mantener estado E1" severity note;
	--	wait for 2 ns;
	--	wait for PERIODO;

		a_t <= '1';
		wait until rising_edge(clk_t);
		wait for 2 ns;
		assert b_t = '0'
			report "Falla transicion E1->A1" severity note;
		wait until rising_edge(clk_t);
		wait for 2 ns;
		assert b_t = '0'
			report "Falla transicion A1->A2" severity note;
		wait for 2 ns;
		wait for PERIODO;

		report "Success!" severity note;
		detener <= true;
		wait;
	end process Prueba;
end architecture test;

descripciones/motor/motor2.vcd
$date
  Tue Apr 05 22:10:38 2022
$end
$version
  GHDL v0
$end
$timescale
  1 fs
$end
$scope module standard $end
$upscope $end
$scope module std_logic_1164 $end
$upscope $end
$scope module numeric_std $end
$upscope $end
$scope module motor2_tb $end
$var reg 1 ! a_t $end
$var reg 1 " b_t $end
$var reg 1 # clk_t $end
$var reg 1 $ rst_t $end
$var reg 1 % detener $end
$scope module dut $end
$var reg 1 & a_i $end
$var reg 1 ' clk $end
$var reg 1 ( rst_i $end
$var reg 1 ) b_o $end
$comment actual is not handled $end
$comment sigue is not handled $end
$upscope $end
$upscope $end
$enddefinitions $end
#0
0!
1"
1#
1$
0%
0&
1'
1(
1)
#10000000
0#
0'
#20000000
0"
1#
1'
0)
#22000000
0$
0(
#30000000
0#
0'
#40000000
1#
1'
#42000000
#50000000
0#
0'
#60000000
1#
1'
#62000000
#70000000
0#
0'
#80000000
1#
1'
#82000000
1!
1&
#90000000
0#
0'
#100000000
1"
1#
1'
1)
#102000000
0!
0&
#110000000
0#
0'
#120000000
1#
1'
#122000000
1!
1&
#130000000
0#
0'
#140000000
0"
1#
1'
0)
#142000000
#150000000
0#
0'
#160000000
1#
1'
#162000000
#164000000
#170000000
0#
0'
#180000000
1"
1#
1'
1)
#184000000
1%
