descripciones/estructural/CompNORn.vhdl
library ieee;
use ieee.std_logic_1164.all;

entity CompNORn is
	generic (N : positive := 4);
	port
	(
		-- Input ports
	entrada_i : in std_logic_vector (N-1 downto 0);
		-- Output ports
	salida_o : out std_logic
	);
end entity CompNORn;

architecture Algoritmica of CompNORn is begin
NORgenerica:
-- Process Statement (optional)
	process (entrada_i)
		variable aux : std_logic;
	begin
		aux := '1';
		for i in N-1 downto 0 loop
			if entrada_i(i)='1' then
				aux := '0';
			end if;
		end loop;
		salida_o <= aux;
	end process NORgenerica;

end architecture Algoritmica;

descripciones/estructural/CompNORn_tb.vhdl
library ieee;
use ieee.std_logic_1164.all;
use ieee.numeric_std.all;

entity CompNORn_tb is
end entity CompNORn_tb;

architecture Test of CompNORn_tb is
	component CompNORn is
		generic( N:positive := 4);
		port( entrada_i : in std_logic_vector (N-1 downto 0);
		salida_o : out std_logic);
	end component CompNORn;

	signal a_t : std_logic_vector (3 downto 0):= (others=>'0');
	signal y_t : std_logic;
-- Declarations (optional)
begin
dut: CompNORn generic map (N=> 4)
port map (entrada_i => a_t,
salida_o => y_t);

Prueba:
process begin
	report "Verificando la compuerta NOR de 4 entradas"
	severity note;

	a_t <= (others=>'0');
	wait for 1 ns;
	assert y_t = '1'
	report "Falla para a=" & integer'image(to_integer(unsigned(a_t)))
	severity failure;

	for i in 1 to 15 loop
		a_t <= std_logic_vector(to_unsigned(i,4));
		wait for 1 ns;
		assert y_t = '0'
		report "Falla para a=" & integer'image(to_integer(unsigned(a_t)))
		severity failure;
	end loop;

	report "Verificación exitosa!"
	severity note;
	wait;
end process Prueba;
end architecture Test;

descripciones/estructural/CompNORn.vcd
$date
  Tue Mar 01 21:33:41 2022
$end
$version
  GHDL v0
$end
$timescale
  1 fs
$end
$scope module standard $end
$upscope $end
$scope module std_logic_1164 $end
$upscope $end
$scope module numeric_std $end
$upscope $end
$scope module compnorn_tb $end
$var reg 4 ! a_t[3:0] $end
$var reg 1 " y_t $end
$scope module dut $end
$var reg 4 # entrada_i[3:0] $end
$var reg 1 $ salida_o $end
$upscope $end
$upscope $end
$enddefinitions $end
#0
b0000 !
1"
b0000 #
1$
#1000000
b0001 !
0"
b0001 #
0$
#2000000
b0010 !
b0010 #
#3000000
b0011 !
b0011 #
#4000000
b0100 !
b0100 #
#5000000
b0101 !
b0101 #
#6000000
b0110 !
b0110 #
#7000000
b0111 !
b0111 #
#8000000
b1000 !
b1000 #
#9000000
b1001 !
b1001 #
#10000000
b1010 !
b1010 #
#11000000
b1011 !
b1011 #
#12000000
b1100 !
b1100 #
#13000000
b1101 !
b1101 #
#14000000
b1110 !
b1110 #
#15000000
b1111 !
b1111 #
