descripciones/robot/robot.vhdl
-- Fecha: robot.vhdl
-- Author: Daniel
-- Date: 04 abril, 2022 - 20:44:56 Argentina Standard Time
library ieee;
use ieee.std_logic_1164.all;

entity robot is
	port
	(
		-- Input ports
	d_i, i_i, a_i, r_i, p_i, b_i : in std_logic;
	clk, rst_i: in std_logic;
		-- Output ports
	d_o, i_o, a_o, r_o, p_o, b_o : out std_logic

	);
end entity robot;

architecture fsm of robot is
	type estado is (d, i, a, r, p, b);
	signal actual, sigue : estado;
begin

secuencial:
process(clk)
begin
	if (clk'event and clk='1') then
		if rst_i='1' then
			actual <= p;
		else
			actual <= sigue;
		end if;
	end if;
end process secuencial;

combinacional:
process(actual, d_i, i_i, a_i, r_i, p_i, b_i)
begin
	case actual is
		when d =>
			r_o<= '0'; i_o<= '0'; a_o<= '0'; p_o<= '0'; b_o<= '0';
			d_o <= '1';
			if (b_i = '0') then
				sigue <= p;
			elsif (a_i = '1') then
				sigue <= a;
			elsif (i_i = '1') then
				sigue <= i;
			elsif (r_i = '1') then
				sigue <= r;
			elsif (p_i = '1') then
				sigue <= p;
			else
				sigue <= d;
			end if;

		when a =>
			d_o<= '0'; i_o<= '0'; r_o<= '0'; p_o<= '0'; b_o<= '0';
			a_o <= '1';
			if (b_i = '0') then
				sigue <= p;
			elsif (d_i = '1') then
				sigue <= d;
			elsif (i_i = '1') then
				sigue <= i;
			elsif (r_i = '1') then
				sigue <= r;
			elsif (p_i = '1') then
				sigue <= p;
			else
				sigue <= a;
			end if;

		when i =>
			d_o<= '0'; r_o<= '0'; a_o<= '0'; p_o<= '0'; b_o<= '0';
			i_o <= '1';
			if (b_i = '0') then
				sigue <= p;
			elsif (a_i = '1') then
				sigue <= a;
			elsif (d_i = '1') then
				sigue <= d;
			elsif (r_i = '1') then
				sigue <= r;
			elsif (p_i = '1') then
				sigue <= p;
			else
				sigue <= i;
			end if;

		when r =>
			d_o<= '0'; i_o<= '0'; a_o<= '0'; p_o<= '0'; b_o<= '0';
			r_o <= '1';
			if (b_i = '0') then
				sigue <= p;
			elsif (d_i = '1') then
				sigue <= d;
			elsif (i_i = '1') then
				sigue <= i;
			elsif (a_i = '1') then
				sigue <= a;
			elsif (p_i = '1') then
				sigue <= p;
			else
				sigue <= r;
			end if;

		when p =>
			d_o<= '0'; i_o<= '0'; a_o<= '0'; r_o<= '0'; b_o<= '0';
			p_o <= '1';
			if (b_i = '0') then
				sigue <= b;
			elsif (d_i = '1') then
				sigue <= d;
			elsif (i_i = '1') then
				sigue <= i;
			elsif (r_i = '1') then
				sigue <= r;
			elsif (a_i = '1') then
				sigue <= a;
			else
				sigue <= p;
			end if;

		when b =>
			d_o<= '0'; i_o<= '0'; a_o<= '0'; r_o<= '0'; p_o<= '0';
			b_o <= '1';
			if (b_i = '1') then
				sigue <= p;
			else
				sigue <= b;
			end if;

		when others =>
			d_o<= '0'; i_o<= '0'; a_o<= '0'; r_o<= '0'; b_o<= '0';
			p_o <= '1';
			sigue <= p;

		end case;
end process;

end architecture fsm;

descripciones/robot/robot_tb.vhdl
-- Fecha: robot_tb.vhdl
-- Author: Daniel
-- Date: 04 abril, 2022 - 21:45:15 Argentina Standard Time
library ieee;
use ieee.std_logic_1164.all;
use ieee.numeric_std.all;

entity robot_tb is
end entity robot_tb;
architecture test of robot_tb is
	component robot is
	port
	(
	d_i, i_i, a_i, r_i, p_i, b_i : in std_logic;
	clk, rst_i : in std_logic;
	d_o, i_o, a_o, r_o, p_o, b_o : out std_logic
	);
	end component robot;

	signal di_t : std_logic := '0';
	signal ii_t : std_logic := '0';
	signal ai_t : std_logic := '0';
	signal ri_t : std_logic := '0';
	signal pi_t : std_logic := '0';
	signal bi_t : std_logic := '1';
	signal do_t : std_logic;
	signal io_t : std_logic;
	signal ao_t : std_logic;
	signal ro_t : std_logic;
	signal po_t : std_logic;
	signal bo_t : std_logic;
	signal clk_t : std_logic := '1';
	signal rst_t : std_logic := '1';
	constant FRECUENCIA : integer := 50;
	constant PERIODO : time := 1 us/FRECUENCIA;
	signal detener : boolean := false;

begin
dut: robot port map
	(
	clk => clk_t,
	rst_i => rst_t,
	d_i => di_t,
	i_i => ii_t,
	a_i => ai_t,
	r_i => ri_t,
	p_i => pi_t,
	b_i => bi_t,
	d_o => do_t,
	i_o => io_t,
	a_o => ao_t,
	r_o => ro_t,
	p_o => po_t,
	b_o => bo_t
	);

reloj:
process begin
	clk_t <= '1', '0' after PERIODO/2;
	wait for PERIODO;
	if detener then
		wait;
	end if;
end process reloj;

Prueba:
	process begin


		report "Verificando robot" severity note;

		-- prueba estado inicial
		-- resetea maquina

		rst_t <= '1';
		wait for PERIODO;
		wait for 2 ns;
		rst_t <= '0';
		wait for PERIODO;
		wait until rising_edge(clk_t);
		assert po_t = '1'
			report "Falla estado inicial P" severity note;
		wait for PERIODO;

		-- prueba pasa a estado B

		bi_t <= '0';
		wait for 2 ns;
		wait for PERIODO;
		wait until rising_edge(clk_t);
		assert bo_t = '1'
			report "Falla transicion P->B" severity note;
		wait for 2 ns;
		wait for PERIODO;

		-- prueba bateria baja

		bi_t <= '1';
		wait until rising_edge(clk_t);
		wait for 2 ns;
		assert po_t = '1'
			report "Falla transicion P->B" severity note;
		wait for 2 ns;
		wait for PERIODO;

		-- prueba avanzar

		ai_t <= '1';
		wait until rising_edge(clk_t);
		wait for 2 ns;
		assert ao_t = '1'
			report "Falla transicion P->A" severity note;
		wait for 2 ns;
		wait for PERIODO;

		-- prueba avanzar sin entrada
		ai_t <= '0';
		wait until rising_edge(clk_t);
		wait for 2 ns;
		assert ao_t = '1'
			report "Falla mantener A" severity note;
		wait for 2 ns;
		wait for PERIODO;

		-- prueba bateria
		bi_t <= '0';
		wait until rising_edge(clk_t);
		wait for 2 ns;
		assert po_t = '1'
			report "Falla transicion A->P" severity note;
		wait for 2 ns;
		wait for PERIODO;
		assert bo_t = '1'
			report "Falla transicion P->B" severity note;
		wait for 2 ns;
		wait for PERIODO;

		report "Success!" severity note;
		detener <= true;
		wait;
	end process Prueba;
end architecture test;

descripciones/robot/robot.vcd
$date
  Tue Apr 05 21:22:01 2022
$end
$version
  GHDL v0
$end
$timescale
  1 fs
$end
$scope module standard $end
$upscope $end
$scope module std_logic_1164 $end
$upscope $end
$scope module numeric_std $end
$upscope $end
$scope module robot_tb $end
$var reg 1 ! di_t $end
$var reg 1 " ii_t $end
$var reg 1 # ai_t $end
$var reg 1 $ ri_t $end
$var reg 1 % pi_t $end
$var reg 1 & bi_t $end
$var reg 1 ' do_t $end
$var reg 1 ( io_t $end
$var reg 1 ) ao_t $end
$var reg 1 * ro_t $end
$var reg 1 + po_t $end
$var reg 1 , bo_t $end
$var reg 1 - clk_t $end
$var reg 1 . rst_t $end
$var reg 1 / detener $end
$scope module dut $end
$var reg 1 0 d_i $end
$var reg 1 1 i_i $end
$var reg 1 2 a_i $end
$var reg 1 3 r_i $end
$var reg 1 4 p_i $end
$var reg 1 5 b_i $end
$var reg 1 6 clk $end
$var reg 1 7 rst_i $end
$var reg 1 8 d_o $end
$var reg 1 9 i_o $end
$var reg 1 : a_o $end
$var reg 1 ; r_o $end
$var reg 1 < p_o $end
$var reg 1 = b_o $end
$comment actual is not handled $end
$comment sigue is not handled $end
$upscope $end
$upscope $end
$enddefinitions $end
#0
0!
0"
0#
0$
0%
1&
1'
0(
0)
0*
0+
0,
1-
1.
0/
00
01
02
03
04
15
16
17
18
09
0:
0;
0<
0=
#10000000
0-
06
#20000000
0'
1+
1-
16
08
1<
#22000000
0.
07
#30000000
0-
06
#40000000
1-
16
#42000000
#50000000
0-
06
#60000000
1-
16
#70000000
0-
06
#80000000
0&
1-
05
16
#82000000
#90000000
0-
06
#100000000
0+
1,
1-
16
0<
1=
#102000000
#110000000
0-
06
#120000000
1-
16
#122000000
#130000000
0-
06
#140000000
1-
16
#142000000
1&
15
#150000000
0-
06
#160000000
1+
0,
1-
16
1<
0=
#162000000
#164000000
#170000000
0-
06
#180000000
1-
16
#184000000
1#
12
#190000000
0-
06
#200000000
1)
0+
1-
16
1:
0<
#202000000
#204000000
#210000000
0-
06
#220000000
1-
16
#224000000
0#
02
#230000000
0-
06
#240000000
1-
16
#242000000
#244000000
#250000000
0-
06
#260000000
1-
16
#264000000
0&
05
#270000000
0-
06
#280000000
0)
1+
1-
16
0:
1<
#282000000
#284000000
#290000000
0-
06
#300000000
0+
1,
1-
16
0<
1=
#304000000
#306000000
#310000000
0-
06
#320000000
1-
16
#326000000
1/
